piper/__init__.py
piper/__main__.py
piper/audio_playback.py
piper/config.py
piper/const.py
piper/download_voices.py
piper/espeakbridge.pyi
piper/espeakbridge.so
piper/http_server.py
piper/patch_voice_with_alignment.py
piper/phoneme_ids.py
piper/phonemize_chinese.py
piper/phonemize_espeak.py
piper/py.typed
piper/voice.py
piper/espeak-ng-data/af_dict
piper/espeak-ng-data/am_dict
piper/espeak-ng-data/an_dict
piper/espeak-ng-data/ar_dict
piper/espeak-ng-data/as_dict
piper/espeak-ng-data/az_dict
piper/espeak-ng-data/ba_dict
piper/espeak-ng-data/be_dict
piper/espeak-ng-data/bg_dict
piper/espeak-ng-data/bn_dict
piper/espeak-ng-data/bpy_dict
piper/espeak-ng-data/bs_dict
piper/espeak-ng-data/ca_dict
piper/espeak-ng-data/chr_dict
piper/espeak-ng-data/cmn_dict
piper/espeak-ng-data/cs_dict
piper/espeak-ng-data/cv_dict
piper/espeak-ng-data/cy_dict
piper/espeak-ng-data/da_dict
piper/espeak-ng-data/de_dict
piper/espeak-ng-data/el_dict
piper/espeak-ng-data/en_dict
piper/espeak-ng-data/eo_dict
piper/espeak-ng-data/es_dict
piper/espeak-ng-data/et_dict
piper/espeak-ng-data/eu_dict
piper/espeak-ng-data/fa_dict
piper/espeak-ng-data/fi_dict
piper/espeak-ng-data/fr_dict
piper/espeak-ng-data/ga_dict
piper/espeak-ng-data/gd_dict
piper/espeak-ng-data/gn_dict
piper/espeak-ng-data/grc_dict
piper/espeak-ng-data/gu_dict
piper/espeak-ng-data/hak_dict
piper/espeak-ng-data/haw_dict
piper/espeak-ng-data/he_dict
piper/espeak-ng-data/hi_dict
piper/espeak-ng-data/hr_dict
piper/espeak-ng-data/ht_dict
piper/espeak-ng-data/hu_dict
piper/espeak-ng-data/hy_dict
piper/espeak-ng-data/ia_dict
piper/espeak-ng-data/id_dict
piper/espeak-ng-data/intonations
piper/espeak-ng-data/io_dict
piper/espeak-ng-data/is_dict
piper/espeak-ng-data/it_dict
piper/espeak-ng-data/ja_dict
piper/espeak-ng-data/jbo_dict
piper/espeak-ng-data/ka_dict
piper/espeak-ng-data/kk_dict
piper/espeak-ng-data/kl_dict
piper/espeak-ng-data/kn_dict
piper/espeak-ng-data/ko_dict
piper_tts-1.4.0.dist-info/METADATA
piper_tts-1.4.0.dist-info/WHEEL
piper_tts-1.4.0.dist-info/entry_points.txt
piper_tts-1.4.0.dist-info/top_level.txt
piper_tts-1.4.0.dist-info/RECORD
piper_tts-1.4.0.dist-info/licenses/COPYING
