Metadata-Version: 2.4
Name: piper-tts
Version: 1.4.0
Summary: Fast and local neural text-to-speech engine
Home-page: http://github.com/OHF-voice/piper1-gpl
Author: The Home Assistant Authors
Author-email: hello@home-assistant.io
License: GPL-3.0-or-later
Keywords: home,assistant,tts,text-to-speech
Classifier: Development Status :: 3 - Alpha
Classifier: Intended Audience :: Developers
Classifier: Topic :: Multimedia :: Sound/Audio :: Speech
Classifier: Programming Language :: Python :: 3.9
Classifier: Programming Language :: Python :: 3.10
Classifier: Programming Language :: Python :: 3.11
Classifier: Programming Language :: Python :: 3.12
Classifier: Programming Language :: Python :: 3.13
Requires-Python: >=3.9
License-File: COPYING
Requires-Dist: onnxruntime<2,>=1
Provides-Extra: train
Requires-Dist: torch<3,>=2; extra == "train"
Requires-Dist: lightning<3,>=2; extra == "train"
Requires-Dist: tensorboard<3,>=2; extra == "train"
Requires-Dist: tensorboardX<3,>=2; extra == "train"
Requires-Dist: jsonargparse[signatures]>=4.27.7; extra == "train"
Requires-Dist: pathvalidate<4,>=3; extra == "train"
Requires-Dist: onnx<2,>=1; extra == "train"
Requires-Dist: pysilero-vad<3,>=2.1; extra == "train"
Requires-Dist: cython<4,>=3; extra == "train"
Requires-Dist: librosa<1; extra == "train"
Provides-Extra: dev
Requires-Dist: black==24.8.0; extra == "dev"
Requires-Dist: flake8==7.1.1; extra == "dev"
Requires-Dist: mypy==1.14.0; extra == "dev"
Requires-Dist: pylint==3.2.7; extra == "dev"
Requires-Dist: pytest==8.3.4; extra == "dev"
Requires-Dist: build==1.2.2; extra == "dev"
Requires-Dist: scikit-build<1; extra == "dev"
Requires-Dist: cmake<4,>=3.18; extra == "dev"
Requires-Dist: ninja<2,>=1; extra == "dev"
Provides-Extra: http
Requires-Dist: flask<4,>=3; extra == "http"
Provides-Extra: alignment
Requires-Dist: onnx<2,>=1; extra == "alignment"
Provides-Extra: zh
Requires-Dist: g2pW<1,>=0.1.1; extra == "zh"
Requires-Dist: sentence-stream<2,>=1.2.1; extra == "zh"
Requires-Dist: unicode-rbnf<3,>=2.4.0; extra == "zh"
Requires-Dist: torch<3,>=2; extra == "zh"
Requires-Dist: requests<3,>=2; extra == "zh"
Dynamic: author
Dynamic: author-email
Dynamic: classifier
Dynamic: home-page
Dynamic: keywords
Dynamic: license
Dynamic: license-file
Dynamic: provides-extra
Dynamic: requires-dist
Dynamic: requires-python
Dynamic: summary
